{"nodes": [{"id": "mlb_api", "label": "mlb-api.ts", "file_type": "code", "source_file": "lib\\mlb-api.ts", "source_location": "L1"}, {"id": "mlb_api_fetchschedule", "label": "fetchSchedule()", "file_type": "code", "source_file": "lib\\mlb-api.ts", "source_location": "L35"}, {"id": "mlb_api_parseip", "label": "parseIP()", "file_type": "code", "source_file": "lib\\mlb-api.ts", "source_location": "L119"}, {"id": "mlb_api_calcfip", "label": "calcFip()", "file_type": "code", "source_file": "lib\\mlb-api.ts", "source_location": "L124"}, {"id": "mlb_api_calckpct", "label": "calcKPct()", "file_type": "code", "source_file": "lib\\mlb-api.ts", "source_location": "L130"}, {"id": "mlb_api_estimateteamplateappearances", "label": "estimateTeamPlateAppearances()", "file_type": "code", "source_file": "lib\\mlb-api.ts", "source_location": "L135"}, {"id": "mlb_api_fetchpitcherstatline", "label": "fetchPitcherStatLine()", "file_type": "code", "source_file": "lib\\mlb-api.ts", "source_location": "L147"}, {"id": "mlb_api_fetchpitcherfipandkpct", "label": "fetchPitcherFipAndKPct()", "file_type": "code", "source_file": "lib\\mlb-api.ts", "source_location": "L158"}, {"id": "mlb_api_fetchpitchermodelstats", "label": "fetchPitcherModelStats()", "file_type": "code", "source_file": "lib\\mlb-api.ts", "source_location": "L167"}, {"id": "mlb_api_fetchteamobp", "label": "fetchTeamOBP()", "file_type": "code", "source_file": "lib\\mlb-api.ts", "source_location": "L201"}, {"id": "mlb_api_fetchteamoffensestats", "label": "fetchTeamOffenseStats()", "file_type": "code", "source_file": "lib\\mlb-api.ts", "source_location": "L206"}, {"id": "mlb_api_extracttopoforderstats", "label": "extractTopOfOrderStats()", "file_type": "code", "source_file": "lib\\mlb-api.ts", "source_location": "L228"}, {"id": "mlb_api_fetchgamelineupstats", "label": "fetchGameLineupStats()", "file_type": "code", "source_file": "lib\\mlb-api.ts", "source_location": "L268"}, {"id": "mlb_api_fetchlinescore", "label": "fetchLinescore()", "file_type": "code", "source_file": "lib\\mlb-api.ts", "source_location": "L296"}], "edges": [{"source": "mlb_api", "target": "poisson", "relation": "imports_from", "confidence": "EXTRACTED", "source_file": "lib\\mlb-api.ts", "source_location": "L1", "weight": 1.0}, {"source": "mlb_api", "target": "mlb_api_fetchschedule", "relation": "contains", "confidence": "EXTRACTED", "source_file": "lib\\mlb-api.ts", "source_location": "L35", "weight": 1.0}, {"source": "mlb_api", "target": "mlb_api_parseip", "relation": "contains", "confidence": "EXTRACTED", "source_file": "lib\\mlb-api.ts", "source_location": "L119", "weight": 1.0}, {"source": "mlb_api", "target": "mlb_api_calcfip", "relation": "contains", "confidence": "EXTRACTED", "source_file": "lib\\mlb-api.ts", "source_location": "L124", "weight": 1.0}, {"source": "mlb_api", "target": "mlb_api_calckpct", "relation": "contains", "confidence": "EXTRACTED", "source_file": "lib\\mlb-api.ts", "source_location": "L130", "weight": 1.0}, {"source": "mlb_api", "target": "mlb_api_estimateteamplateappearances", "relation": "contains", "confidence": "EXTRACTED", "source_file": "lib\\mlb-api.ts", "source_location": "L135", "weight": 1.0}, {"source": "mlb_api", "target": "mlb_api_fetchpitcherstatline", "relation": "contains", "confidence": "EXTRACTED", "source_file": "lib\\mlb-api.ts", "source_location": "L147", "weight": 1.0}, {"source": "mlb_api", "target": "mlb_api_fetchpitcherfipandkpct", "relation": "contains", "confidence": "EXTRACTED", "source_file": "lib\\mlb-api.ts", "source_location": "L158", "weight": 1.0}, {"source": "mlb_api", "target": "mlb_api_fetchpitchermodelstats", "relation": "contains", "confidence": "EXTRACTED", "source_file": "lib\\mlb-api.ts", "source_location": "L167", "weight": 1.0}, {"source": "mlb_api", "target": "mlb_api_fetchteamobp", "relation": "contains", "confidence": "EXTRACTED", "source_file": "lib\\mlb-api.ts", "source_location": "L201", "weight": 1.0}, {"source": "mlb_api", "target": "mlb_api_fetchteamoffensestats", "relation": "contains", "confidence": "EXTRACTED", "source_file": "lib\\mlb-api.ts", "source_location": "L206", "weight": 1.0}, {"source": "mlb_api", "target": "mlb_api_extracttopoforderstats", "relation": "contains", "confidence": "EXTRACTED", "source_file": "lib\\mlb-api.ts", "source_location": "L228", "weight": 1.0}, {"source": "mlb_api", "target": "mlb_api_fetchgamelineupstats", "relation": "contains", "confidence": "EXTRACTED", "source_file": "lib\\mlb-api.ts", "source_location": "L268", "weight": 1.0}, {"source": "mlb_api", "target": "mlb_api_fetchlinescore", "relation": "contains", "confidence": "EXTRACTED", "source_file": "lib\\mlb-api.ts", "source_location": "L296", "weight": 1.0}, {"source": "mlb_api_calcfip", "target": "mlb_api_parseip", "relation": "calls", "confidence": "EXTRACTED", "source_file": "lib\\mlb-api.ts", "source_location": "L125", "weight": 1.0}, {"source": "mlb_api_fetchpitcherfipandkpct", "target": "mlb_api_fetchpitchermodelstats", "relation": "calls", "confidence": "EXTRACTED", "source_file": "lib\\mlb-api.ts", "source_location": "L163", "weight": 1.0}, {"source": "mlb_api_fetchpitchermodelstats", "target": "mlb_api_fetchpitcherstatline", "relation": "calls", "confidence": "EXTRACTED", "source_file": "lib\\mlb-api.ts", "source_location": "L172", "weight": 1.0}, {"source": "mlb_api_fetchpitchermodelstats", "target": "mlb_api_parseip", "relation": "calls", "confidence": "EXTRACTED", "source_file": "lib\\mlb-api.ts", "source_location": "L183", "weight": 1.0}, {"source": "mlb_api_fetchpitchermodelstats", "target": "mlb_api_calcfip", "relation": "calls", "confidence": "EXTRACTED", "source_file": "lib\\mlb-api.ts", "source_location": "L185", "weight": 1.0}, {"source": "mlb_api_fetchpitchermodelstats", "target": "mlb_api_calckpct", "relation": "calls", "confidence": "EXTRACTED", "source_file": "lib\\mlb-api.ts", "source_location": "L186", "weight": 1.0}, {"source": "mlb_api_fetchteamobp", "target": "mlb_api_fetchteamoffensestats", "relation": "calls", "confidence": "EXTRACTED", "source_file": "lib\\mlb-api.ts", "source_location": "L202", "weight": 1.0}, {"source": "mlb_api_fetchteamoffensestats", "target": "mlb_api_estimateteamplateappearances", "relation": "calls", "confidence": "EXTRACTED", "source_file": "lib\\mlb-api.ts", "source_location": "L219", "weight": 1.0}, {"source": "mlb_api_fetchgamelineupstats", "target": "mlb_api_extracttopoforderstats", "relation": "calls", "confidence": "EXTRACTED", "source_file": "lib\\mlb-api.ts", "source_location": "L282", "weight": 1.0}]}